quickqr/QR2.py
quickqr/__init__.py
quickqr-0.3.0.dist-info/METADATA
quickqr-0.3.0.dist-info/WHEEL
quickqr-0.3.0.dist-info/top_level.txt
quickqr-0.3.0.dist-info/RECORD
